ShengchengDuikangWangluoXiangmuChuyiFix1/README.md
ShengchengDuikangWangluoXiangmuChuyiFix1/__init__.py
ShengchengDuikangWangluoXiangmuChuyiFix1/__main__.py
ShengchengDuikangWangluoXiangmuChuyiFix1/file.epub
ShengchengDuikangWangluoXiangmuChuyiFix1/index.html
ShengchengDuikangWangluoXiangmuChuyiFix1/css/__init__.py
ShengchengDuikangWangluoXiangmuChuyiFix1/css/annotations.css
ShengchengDuikangWangluoXiangmuChuyiFix1/css/main.css
ShengchengDuikangWangluoXiangmuChuyiFix1/css/normalize.css
ShengchengDuikangWangluoXiangmuChuyiFix1/css/popup.css
ShengchengDuikangWangluoXiangmuChuyiFix1/font/__init__.py
ShengchengDuikangWangluoXiangmuChuyiFix1/font/fontello.eot
ShengchengDuikangWangluoXiangmuChuyiFix1/font/fontello.svg
ShengchengDuikangWangluoXiangmuChuyiFix1/font/fontello.ttf
ShengchengDuikangWangluoXiangmuChuyiFix1/font/fontello.woff
ShengchengDuikangWangluoXiangmuChuyiFix1/img/__init__.py
ShengchengDuikangWangluoXiangmuChuyiFix1/img/annotator-glyph-sprite.png
ShengchengDuikangWangluoXiangmuChuyiFix1/img/annotator-icon-sprite.png
ShengchengDuikangWangluoXiangmuChuyiFix1/img/apple-touch-icon.png
ShengchengDuikangWangluoXiangmuChuyiFix1/img/cancelfullscreen.png
ShengchengDuikangWangluoXiangmuChuyiFix1/img/close.png
ShengchengDuikangWangluoXiangmuChuyiFix1/img/fullscreen.png
ShengchengDuikangWangluoXiangmuChuyiFix1/img/loader.gif
ShengchengDuikangWangluoXiangmuChuyiFix1/img/menu-icon.png
ShengchengDuikangWangluoXiangmuChuyiFix1/img/save.png
ShengchengDuikangWangluoXiangmuChuyiFix1/img/saved.png
ShengchengDuikangWangluoXiangmuChuyiFix1/img/settings-s.png
ShengchengDuikangWangluoXiangmuChuyiFix1/img/settings.png
ShengchengDuikangWangluoXiangmuChuyiFix1/img/star.png
ShengchengDuikangWangluoXiangmuChuyiFix1/js/__init__.py
ShengchengDuikangWangluoXiangmuChuyiFix1/js/epub.js
ShengchengDuikangWangluoXiangmuChuyiFix1/js/epub.min.js
ShengchengDuikangWangluoXiangmuChuyiFix1/js/epub.min.map
ShengchengDuikangWangluoXiangmuChuyiFix1/js/hooks.min.js
shengcheng_duikang_wangluo_xiangmu_chuyi_fix1-2025.3.24.1.dist-info/METADATA
shengcheng_duikang_wangluo_xiangmu_chuyi_fix1-2025.3.24.1.dist-info/WHEEL
shengcheng_duikang_wangluo_xiangmu_chuyi_fix1-2025.3.24.1.dist-info/entry_points.txt
shengcheng_duikang_wangluo_xiangmu_chuyi_fix1-2025.3.24.1.dist-info/top_level.txt
shengcheng_duikang_wangluo_xiangmu_chuyi_fix1-2025.3.24.1.dist-info/RECORD
